pyAQIplot/AQI_plot.py
pyAQIplot/__init__.py
pyAQIplot/colorbar.py
pyAQIplot/structure.py
pyAQIplot-0.1.3.dist-info/LICENSE.txt
pyAQIplot-0.1.3.dist-info/METADATA
pyAQIplot-0.1.3.dist-info/WHEEL
pyAQIplot-0.1.3.dist-info/top_level.txt
pyAQIplot-0.1.3.dist-info/RECORD
